{"nodes": [{"id": "references_sources_articles_2025-08-17_164534_\u5b9a\u4f4d\u4e0e\u7acb\u573a\u7f8e\u5e1d\u7684\u82b1\u62db\u4e0e\u90e8\u5206\u5154\u7684\u4e0d\u81ea\u4fe1", "label": "\u5b9a\u4f4d\u4e0e\u7acb\u573a--\u7f8e\u5e1d\u7684\u82b1\u62db\u4e0e\u90e8\u5206\u5154\u7684\u4e0d\u81ea\u4fe1", "file_type": "document", "source_file": "references/sources/articles/2025-08-17 164534_\u51b0\u51b0\u5c0f\u7f8e_\u5b9a\u4f4d\u4e0e\u7acb\u573a--\u7f8e\u5e1d\u7684\u82b1\u62db\u4e0e\u90e8\u5206\u5154\u7684\u4e0d\u81ea\u4fe1.md", "source_location": null, "source_url": "https://xueqiu.com/7143769715/347427628", "captured_at": null, "author": "\u51b0\u51b0\u5c0f\u7f8e", "contributor": null}], "edges": [{"source": "references_sources_articles_2025-08-17_164534_\u5b9a\u4f4d\u4e0e\u7acb\u573a\u7f8e\u5e1d\u7684\u82b1\u62db\u4e0e\u90e8\u5206\u5154\u7684\u4e0d\u81ea\u4fe1", "target": "concept_\u7c73\u7684\u5ddd\u9a6c\u65b0\u653f\u6218\u7565\u610f\u56fe", "relation": "conceptually_related_to", "confidence": "EXTRACTED", "confidence_score": 0.95, "source_file": "references/sources/articles/2025-08-17 164534_\u51b0\u51b0\u5c0f\u7f8e_\u5b9a\u4f4d\u4e0e\u7acb\u573a--\u7f8e\u5e1d\u7684\u82b1\u62db\u4e0e\u90e8\u5206\u5154\u7684\u4e0d\u81ea\u4fe1.md", "source_location": null, "weight": 1.0}, {"source": "references_sources_articles_2025-08-17_164534_\u5b9a\u4f4d\u4e0e\u7acb\u573a\u7f8e\u5e1d\u7684\u82b1\u62db\u4e0e\u90e8\u5206\u5154\u7684\u4e0d\u81ea\u4fe1", "target": "concept_\u5154\u7c73\u79d1\u6280\u4e0eAi\u535a\u5f08", "relation": "conceptually_related_to", "confidence": "EXTRACTED", "confidence_score": 0.9, "source_file": "references/sources/articles/2025-08-17 164534_\u51b0\u51b0\u5c0f\u7f8e_\u5b9a\u4f4d\u4e0e\u7acb\u573a--\u7f8e\u5e1d\u7684\u82b1\u62db\u4e0e\u90e8\u5206\u5154\u7684\u4e0d\u81ea\u4fe1.md", "source_location": null, "weight": 1.0}, {"source": "references_sources_articles_2025-08-17_164534_\u5b9a\u4f4d\u4e0e\u7acb\u573a\u7f8e\u5e1d\u7684\u82b1\u62db\u4e0e\u90e8\u5206\u5154\u7684\u4e0d\u81ea\u4fe1", "target": "references_sources_articles_2025-08-16_151943_\u4fe1\u606f\u7684\u91d1\u878d\u610f\u4e49\u5341\u4e00", "relation": "references", "confidence": "EXTRACTED", "confidence_score": 0.85, "source_file": "references/sources/articles/2025-08-17 164534_\u51b0\u51b0\u5c0f\u7f8e_\u5b9a\u4f4d\u4e0e\u7acb\u573a--\u7f8e\u5e1d\u7684\u82b1\u62db\u4e0e\u90e8\u5206\u5154\u7684\u4e0d\u81ea\u4fe1.md", "source_location": null, "weight": 1.0}], "hyperedges": []}