{"nodes": [{"id": "references_sources_articles_2026-06-22_110303_concept_three_pillar_allocation", "label": "Three Pillar Allocation (Pillar Industries + Strategic Resources + Emerging Industries)", "file_type": "concept", "source_file": "references/sources/articles/2026-06-22 110303_\u51b0\u51b0\u5c0f\u7f8e_\u5f53\u56fd\u5bb6\u961f\u9000\u51faETF\uff0c\u5e02\u573a\u7684\u6ce2\u52a8\u5c31\u52a0\u5927\u4e86\u3002\u6307\u6570\u4e5f\u5230\u8fbe\u76ee\u68074200\u3002\u6211\u57282023\u5e74\u7684\u5224\u65ad\u5c31\u5df2\u7ecf\u5230\u4e86\u7ec8\u70b9\u3002\u90a3\u4e482023\u5e74\u7684\u5224\u65ad.md", "source_location": null, "source_url": null, "captured_at": null, "author": "\u51b0\u51b0\u5c0f\u7f8e", "contributor": null}], "edges": [{"source": "references_sources_articles_2026-06-22_110303_concept_three_pillar_allocation", "target": "references_sources_articles_2026-06-22_154144_concept_strategic_resource_rebalance", "relation": "references", "confidence": "EXTRACTED", "confidence_score": 0.9, "source_file": "references/sources/articles/2026-06-22 110303_\u51b0\u51b0\u5c0f\u7f8e_\u5f53\u56fd\u5bb6\u961f\u9000\u51faETF\uff0c\u5e02\u573a\u7684\u6ce2\u52a8\u5c31\u52a0\u5927\u4e86\u3002\u6307\u6570\u4e5f\u5230\u8fbe\u76ee\u68074200\u3002\u6211\u57282023\u5e74\u7684\u5224\u65ad\u5c31\u5df2\u7ecf\u5230\u4e86\u7ec8\u70b9\u3002\u90a3\u4e482023\u5e74\u7684\u5224\u65ad.md", "source_location": null, "weight": 0.9}], "hyperedges": []}