{"nodes": [{"id": "bingbingxiaomei_perspective_references_sources_articles_2026_06_13_113141_20229__three_year_investment_horizon", "label": "Three-Year Investment Horizon", "file_type": "rationale", "source_file": "references/sources/articles/2026-06-13 113141_\u51b0\u51b0\u5c0f\u7f8e_\u4f60\u4f1a\u53d1\u73b0\uff0c\u5e16\u5b50\u603b\u662f\u8bf4\u4e09\u5e74\u524d\u79cd\u7684\u79cd\u5b50\u3002\u8fd9\u662f\u56e0\u4e3a\u6211\u624d\u66f4\u65b0\u4e09\u5e74\u3002\u5341\u5e74\u524d\u7684\u79cd\u5b50\u4f60\u6ca1\u53d1\u770b\u89c1\u800c\u5df2\u3002\u6211\u53d1\u5e16\u662f20229\u6708\u3002\u6b63\u5f0f\u66f4\u65b0\u4f53.md", "source_location": null, "source_url": "https://xueqiu.com/7143769715/394573811", "captured_at": "2026-06-13 22:41:20", "author": "\u51b0\u51b0\u5c0f\u7f8e", "contributor": null}], "edges": [{"source": "bingbingxiaomei_perspective_references_sources_articles_2026_06_11_214609_80_500_350_350_80__long_term_industry_research", "target": "bingbingxiaomei_perspective_references_sources_articles_2026_06_13_113141_20229__three_year_investment_horizon", "relation": "semantically_similar_to", "confidence": "INFERRED", "confidence_score": 0.85, "source_file": "references/sources/articles/2026-06-13 113141_\u51b0\u51b0\u5c0f\u7f8e_\u4f60\u4f1a\u53d1\u73b0\uff0c\u5e16\u5b50\u603b\u662f\u8bf4\u4e09\u5e74\u524d\u79cd\u7684\u79cd\u5b50\u3002\u8fd9\u662f\u56e0\u4e3a\u6211\u624d\u66f4\u65b0\u4e09\u5e74\u3002\u5341\u5e74\u524d\u7684\u79cd\u5b50\u4f60\u6ca1\u53d1\u770b\u89c1\u800c\u5df2\u3002\u6211\u53d1\u5e16\u662f20229\u6708\u3002\u6b63\u5f0f\u66f4\u65b0\u4f53.md", "source_location": null, "weight": 1.0}], "hyperedges": []}