{"nodes": [{"id": "bingbingxiaomei_perspective_references_sources_articles_2024_05_05_161919_document", "label": "\u8bfb\u4e66\u4e0e\u7ecf\u6d4e\u7406\u8bba\u4f53\u7cfb", "file_type": "document", "source_file": "references/sources/articles/2024-05-05 161919_\u51b0\u51b0\u5c0f\u7f8e_\u65f6\u5e38\u770b\u5230\u6709\u4eba\u95ee\u8bfb\u4e66\u7684\u95ee\u9898\uff0c\u5982\u679c\u4ee5\u4e00\u672c\u597d\u4e66\u6216\u8005\u7ecf\u6d4e\u7406\u8bba\u4f53\u7cfb\u4f5c\u4e3a\u6839\u57fa\uff0c\u6839\u636e\u5927\u5e08\u7684\u7814\u7a76\u8def\u7ebf\u53bb\u8bfb\u4e66\u3002\u66f4\u5bb9\u6613\u4f53\u4f1a\u5230\u5927\u5e08\u9047\u89c1\u7684\u7ecf\u6d4e\u4e0e.md", "source_location": null, "source_url": "https://xueqiu.com/7143769715/288805717", "captured_at": "2026-06-23 00:20:20", "author": ["[[\u51b0\u51b0\u5c0f\u7f8e]]"], "contributor": null}, {"id": "bingbingxiaomei_perspective_references_sources_articles_2024_05_05_161919_genealogical_reading", "label": "Genealogical Reading", "file_type": "concept", "source_file": "references/sources/articles/2024-05-05 161919_\u51b0\u51b0\u5c0f\u7f8e_\u65f6\u5e38\u770b\u5230\u6709\u4eba\u95ee\u8bfb\u4e66\u7684\u95ee\u9898\uff0c\u5982\u679c\u4ee5\u4e00\u672c\u597d\u4e66\u6216\u8005\u7ecf\u6d4e\u7406\u8bba\u4f53\u7cfb\u4f5c\u4e3a\u6839\u57fa\uff0c\u6839\u636e\u5927\u5e08\u7684\u7814\u7a76\u8def\u7ebf\u53bb\u8bfb\u4e66\u3002\u66f4\u5bb9\u6613\u4f53\u4f1a\u5230\u5927\u5e08\u9047\u89c1\u7684\u7ecf\u6d4e\u4e0e.md", "source_location": null, "source_url": "https://xueqiu.com/7143769715/288805717", "captured_at": "2026-06-23 00:20:20", "author": ["[[\u51b0\u51b0\u5c0f\u7f8e]]"], "contributor": null, "rationale": "Understanding a theory requires following its cited intellectual lineage and related practical fields."}], "edges": [{"source": "bingbingxiaomei_perspective_references_sources_articles_2024_05_05_161919_document", "target": "bingbingxiaomei_perspective_references_sources_articles_2024_05_05_161919_genealogical_reading", "relation": "references", "confidence": "EXTRACTED", "confidence_score": 1.0, "source_file": "references/sources/articles/2024-05-05 161919_\u51b0\u51b0\u5c0f\u7f8e_\u65f6\u5e38\u770b\u5230\u6709\u4eba\u95ee\u8bfb\u4e66\u7684\u95ee\u9898\uff0c\u5982\u679c\u4ee5\u4e00\u672c\u597d\u4e66\u6216\u8005\u7ecf\u6d4e\u7406\u8bba\u4f53\u7cfb\u4f5c\u4e3a\u6839\u57fa\uff0c\u6839\u636e\u5927\u5e08\u7684\u7814\u7a76\u8def\u7ebf\u53bb\u8bfb\u4e66\u3002\u66f4\u5bb9\u6613\u4f53\u4f1a\u5230\u5927\u5e08\u9047\u89c1\u7684\u7ecf\u6d4e\u4e0e.md", "source_location": null, "weight": 1.0}], "hyperedges": []}