{"nodes": [{"id": "bingbingxiaomei_perspective_references_sources_articles_2026_05_19_151038___________________________________________________________________article", "label": "National Confidence and Investment Outlook", "file_type": "document", "source_file": "references/sources/articles/2026-05-19 151038_\u51b0\u51b0\u5c0f\u7f8e_\u6000\u7591\u6211\u53ef\u4ee5\uff0c\u6000\u7591\u56fd\u5bb6\u5c31\u4e0d\u5bf9\u4e86\u3002\u8fd9\u662f\u7b2c\u4e09\u70b9\u5fe0\u544a\u3002\u5982\u679c\u56fd\u5bb6\u90fd\u7a77\u56f0\uff0c\u4e2a\u4eba\u54ea\u91cc\u8fd8\u6709\u5bcc\u88d5\u7684\u5e0c\u671b\u4e0e\u673a\u4f1a\u3002\u8fd9\u4e48\u7b80\u5355\u7684\u9053\u7406\u3002\u5495\u5495\u560e\u560e\u3002\u76f8.md", "source_location": null, "source_url": "https://xueqiu.com/7143769715/389699235", "captured_at": "2026-05-19 15:10:38", "author": "\u51b0\u51b0\u5c0f\u7f8e", "contributor": null}], "edges": [], "hyperedges": []}